sumador_un_bit.v
module sumador_un_bit (
    input A,       // Entrada A
    input B,       // Entrada B
    input Ci,      // Entrada Acarreo 
    output So,     // Salida Suma
    output Co      // Salida Acarreo 
);

    wire x_ab;    // Resultado de A XOR B
    wire cout_t;  // Acarreo 
    wire a_ab;    // Acarreo generado por A y B 

    xor (x_ab, A, B);
    xor (So, x_ab, Ci);
    and (cout_t, x_ab, Ci);
    and (a_ab, A, B);
    or (Co, cout_t, a_ab);

endmodule

sumador_restador_4_bits.v
// Asegúrate de que "sumador_un_bit.v" esté en la misma carpeta
`include "sumador_un_bit.v"

module sumador_restador_4_bits (
    input [3:0] A,   // Entrada A (4 bits)
    input [3:0] B,   // Entrada B (4 bits)
    input Sel,       // Señal de control: 0 para Suma, 1 para Resta (Complemento a 2)
    output [3:0] So, // Salida Suma/Resta (4 bits)
    output Co        // Acarreo de Salida Final (Indica signo si es resta)
);

    wire [4:0] c;
    wire [3:0] B_xor; // Cable interno para conectar la salida de las XOR al sumador

    // Asignamos la señal de control (Sel) al acarreo de entrada inicial. 
    // Si Sel=1 (resta), suma el "1" necesario para el complemento a 2.
    assign c[0] = Sel;

    // --- GENERATE FOR: Instanciación automática ---
    genvar i; // Variable especial para generación de hardware
    generate
        for (i = 0; i < 4; i = i + 1) begin : etapa
            
            // Compuerta XOR: Invierte el bit de B si Sel es 1 (Paso 1 del complemento a 2)
            assign B_xor[i] = B[i] ^ Sel;

            // Instanciamos el sumador de 1 bit 4 veces
            sumador_un_bit inst (
                .A(A[i]),      // Bit i de A
                .B(B_xor[i]),  // Bit i de B modificado por la compuerta XOR
                .Ci(c[i]),     // Acarreo actual (entra)
                .So(So[i]),    // Suma resultante (sale)
                .Co(c[i+1])    // Acarreo siguiente (sale hacia la próxima etapa)
            );
        end
    endgenerate

    // Asignamos el último cable (c[4]) a la salida final Co
    assign Co = c[4];

endmodule

sumador_restador_tb.v
`include "sumador_restador_4_bits.v"
`timescale 1ns/1ns

module sumador_restador_tb();

    reg [3:0] A_tb, B_tb;
    reg Sel_tb;
    wire [3:0] So_tb;
    wire Co_tb;

    integer i, j, k;
    reg [4:0] resultado_esperado;

    // --- SOLUCIÓN AL ERROR DE $MONITOR ---
    // Creamos señales simples para que el monitor no se queje
    wire [31:0] modo_str = (Sel_tb) ? "REST" : "SUMA"; // Guardamos el texto en un cable
    wire signed [3:0] So_signed = So_tb;               // Convertimos a signo en un cable

    sumador_restador_4_bits uut (
        .A(A_tb),
        .B(B_tb),
        .Sel(Sel_tb),
        .So(So_tb),
        .Co(Co_tb)
    );

    initial begin
        $dumpfile("sumador_restador.vcd");
        $dumpvars(0, sumador_restador_tb);
        
        // Ahora el monitor solo recibe "señales simples"
        $monitor("Time=%0t | Modo=%s | A=%d | B=%d || Co=%b | So=%b | Dec=%d", 
                  $time, modo_str, A_tb, B_tb, Co_tb, So_tb, So_signed);
    end

    initial begin
        for (k = 0; k < 2; k = k + 1) begin
            for (i = 0; i < 16; i = i + 1) begin
                for (j = 0; j < 16; j = j + 1) begin
                    Sel_tb = k;
                    A_tb = i;
                    B_tb = j;
                    #10; 

                    if (Sel_tb == 0) 
                        resultado_esperado = i + j;
                    else 
                        resultado_esperado = i + (~j & 4'b1111) + 1;

                    if ({Co_tb, So_tb} !== resultado_esperado[4:0]) begin
                        $display("ERROR: A=%d B=%d | Exp=%b Obt=%b", 
                                  A_tb, B_tb, resultado_esperado[4:0], {Co_tb, So_tb});
                    end
                end
            end
        end

        $display("---------------------------------------------------------------");
        $display("Test completado con éxito.");
        $display("---------------------------------------------------------------");
        $finish;
    end

endmodule

build/sumador_restador.vcd
$date
	Fri Mar 13 21:56:05 2026
$end
$version
	Icarus Verilog
$end
$timescale
	1ns
$end
$scope module sumador_restador_tb $end
$var wire 4 ! So_signed [3:0] $end
$var wire 32 " modo_str [31:0] $end
$var wire 4 # So_tb [3:0] $end
$var wire 1 $ Co_tb $end
$var reg 4 % A_tb [3:0] $end
$var reg 4 & B_tb [3:0] $end
$var reg 1 ' Sel_tb $end
$var reg 5 ( resultado_esperado [4:0] $end
$var integer 32 ) i [31:0] $end
$var integer 32 * j [31:0] $end
$var integer 32 + k [31:0] $end
$scope module uut $end
$var wire 4 , A [3:0] $end
$var wire 4 - B [3:0] $end
$var wire 1 ' Sel $end
$var wire 5 . c [4:0] $end
$var wire 4 / So [3:0] $end
$var wire 1 $ Co $end
$var wire 4 0 B_xor [3:0] $end
$scope begin etapa[0] $end
$scope module inst $end
$var wire 1 1 A $end
$var wire 1 2 B $end
$var wire 1 3 Ci $end
$var wire 1 4 Co $end
$var wire 1 5 So $end
$var wire 1 6 a_ab $end
$var wire 1 7 cout_t $end
$var wire 1 8 x_ab $end
$upscope $end
$upscope $end
$scope begin etapa[1] $end
$scope module inst $end
$var wire 1 9 A $end
$var wire 1 : B $end
$var wire 1 ; Ci $end
$var wire 1 < Co $end
$var wire 1 = So $end
$var wire 1 > a_ab $end
$var wire 1 ? cout_t $end
$var wire 1 @ x_ab $end
$upscope $end
$upscope $end
$scope begin etapa[2] $end
$scope module inst $end
$var wire 1 A A $end
$var wire 1 B B $end
$var wire 1 C Ci $end
$var wire 1 D Co $end
$var wire 1 E So $end
$var wire 1 F a_ab $end
$var wire 1 G cout_t $end
$var wire 1 H x_ab $end
$upscope $end
$upscope $end
$scope begin etapa[3] $end
$scope module inst $end
$var wire 1 I A $end
$var wire 1 J B $end
$var wire 1 K Ci $end
$var wire 1 L Co $end
$var wire 1 M So $end
$var wire 1 N a_ab $end
$var wire 1 O cout_t $end
$var wire 1 P x_ab $end
$upscope $end
$upscope $end
$upscope $end
$upscope $end
$enddefinitions $end
#0
$dumpvars
0P
0O
0N
0M
0L
0K
0J
0I
0H
0G
0F
0E
0D
0C
0B
0A
0@
0?
0>
0=
0<
0;
0:
09
08
07
06
05
04
03
02
01
b0 0
b0 /
b0 .
b0 -
b0 ,
b0 +
b0 *
b0 )
bx (
0'
b0 &
b0 %
0$
b0 #
b1010011010101010100110101000001 "
b0 !
$end
#10
b1 !
b1 #
b1 /
15
18
12
b1 0
b1 &
b1 -
b1 *
b0 (
#20
05
b10 !
b10 #
b10 /
1=
08
1@
02
1:
b10 0
b10 &
b10 -
b10 *
b1 (
#30
b11 !
b11 #
b11 /
15
18
12
b11 0
b11 &
b11 -
b11 *
b10 (
#40
05
0=
b100 !
b100 #
b100 /
1E
08
0@
1H
02
0:
1B
b100 0
b100 &
b100 -
b100 *
b11 (
#50
b101 !
b101 #
b101 /
15
18
12
b101 0
b101 &
b101 -
b101 *
b100 (
#60
05
b110 !
b110 #
b110 /
1=
08
1@
02
1:
b110 0
b110 &
b110 -
b110 *
b101 (
#70
b111 !
b111 #
b111 /
15
18
12
b111 0
b111 &
b111 -
b111 *
b110 (
#80
05
0=
0E
b1000 !
b1000 #
b1000 /
1M
08
0@
0H
1P
02
0:
0B
1J
b1000 0
b1000 &
b1000 -
b1000 *
b111 (
#90
b1001 !
b1001 #
b1001 /
15
18
12
b1001 0
b1001 &
b1001 -
b1001 *
b1000 (
#100
05
b1010 !
b1010 #
b1010 /
1=
08
1@
02
1:
b1010 0
b1010 &
b1010 -
b1010 *
b1001 (
#110
b1011 !
b1011 #
b1011 /
15
18
12
b1011 0
b1011 &
b1011 -
b1011 *
b1010 (
#120
05
0=
b1100 !
b1100 #
b1100 /
1E
08
0@
1H
02
0:
1B
b1100 0
b1100 &
b1100 -
b1100 *
b1011 (
#130
b1101 !
b1101 #
b1101 /
15
18
12
b1101 0
b1101 &
b1101 -
b1101 *
b1100 (
#140
05
b1110 !
b1110 #
b1110 /
1=
08
1@
02
1:
b1110 0
b1110 &
b1110 -
b1110 *
b1101 (
#150
b1111 !
b1111 #
b1111 /
15
18
12
b1111 0
b1111 &
b1111 -
b1111 *
b1110 (
#160
0=
0E
0M
0@
0H
0P
0;
02
0:
0B
0J
b1 !
b1 #
b1 /
15
b0 .
04
b0 0
18
06
11
b0 &
b0 -
b1 %
b1 ,
b1 )
b0 *
b1111 (
#170
1=
1;
b10 !
b10 #
b10 /
05
b10 .
14
08
16
12
b1 0
b1 &
b1 -
b1 *
b1 (
#180
0E
0C
0;
0<
15
b0 .
04
b11 !
b11 #
b11 /
1=
0?
18
06
1@
02
1:
b10 0
b10 &
b10 -
b10 *
b10 (
#190
1E
1C
1<
0=
1?
1;
b100 !
b100 #
b100 /
05
b110 .
14
08
16
12
b11 0
b11 &
b11 -
b11 *
b11 (
#200
0M
0C
0K
0;
0<
0D
15
b0 .
04
0=
0?
b101 !
b101 #
b101 /
1E
0G
18
06
0@
1H
02
0:
1B
b100 0
b100 &
b100 -
b100 *
b100 (
#210
1=
1;
b110 !
b110 #
b110 /
05
b10 .
14
08
16
12
b101 0
b101 &
b101 -
b101 *
b101 (
#220
0M
0K
0D
1E
0G
0C
0;
0<
15
b0 .
04
b111 !
b111 #
b111 /
1=
0?
18
06
1@
02
1:
b110 0
b110 &
b110 -
b110 *
b110 (
#230
1M
1K
1D
0E
1G
1C
1<
0=
1?
1;
b1000 !
b1000 #
b1000 /
05
b1110 .
14
08
16
12
b111 0
b111 &
b111 -
b111 *
b111 (
#240
0C
0K
0$
0;
0<
0D
0L
15
b0 .
04
0=
0?
0E
0G
b1001 !
b1001 #
b1001 /
1M
0O
18
06
0@
0H
1P
02
0:
0B
1J
b1000 0
b1000 &
b1000 -
b1000 *
b1000 (
#250
1=
1;
b1010 !
b1010 #
b1010 /
05
b10 .
14
08
16
12
b1001 0
b1001 &
b1001 -
b1001 *
b1001 (
#260
0E
0C
0;
0<
15
b0 .
04
b1011 !
b1011 #
b1011 /
1=
0?
18
06
1@
02
1:
b1010 0
b1010 &
b1010 -
b1010 *
b1010 (
#270
1E
1C
1<
0=
1?
1;
b1100 !
b1100 #
b1100 /
05
b110 .
14
08
16
12
b1011 0
b1011 &
b1011 -
b1011 *
b1011 (
#280
0$
0L
1M
0O
0C
0K
0;
0<
0D
15
b0 .
04
0=
0?
b1101 !
b1101 #
b1101 /
1E
0G
18
06
0@
1H
02
0:
1B
b1100 0
b1100 &
b1100 -
b1100 *
b1100 (
#290
1=
1;
b1110 !
b1110 #
b1110 /
05
b10 .
14
08
16
12
b1101 0
b1101 &
b1101 -
b1101 *
b1101 (
#300
0$
0L
1M
0O
0K
0D
1E
0G
0C
0;
0<
15
b0 .
04
b1111 !
b1111 #
b1111 /
1=
0?
18
06
1@
02
1:
b1110 0
b1110 &
b1110 -
b1110 *
b1110 (
#310
1$
1L
0M
1O
1K
1D
0E
1G
1C
1<
0=
1?
1;
b0 !
b0 #
b0 /
05
b11110 .
14
08
16
12
b1111 0
b1111 &
b1111 -
b1111 *
b1111 (
#320
0K
0$
0C
0D
0L
0<
0E
0G
0M
0O
0H
0P
0;
02
0:
0B
0J
05
b0 .
04
b10 !
b10 #
b10 /
1=
0?
b0 0
08
06
1@
0>
01
19
b0 &
b0 -
b10 %
b10 ,
b10 )
b0 *
b10000 (
#330
b11 !
b11 #
b11 /
15
18
12
b1 0
b1 &
b1 -
b1 *
b10 (
#340
1E
1C
05
b100 !
b100 #
b100 /
0=
b100 .
1<
08
0@
1>
02
1:
b10 0
b10 &
b10 -
b10 *
b11 (
#350
b101 !
b101 #
b101 /
15
18
12
b11 0
b11 &
b11 -
b11 *
b100 (
#360
0M
0K
0C
0D
05
1=
b0 .
0<
b110 !
b110 #
b110 /
1E
0G
08
1@
0>
1H
02
0:
1B
b100 0
b100 &
b100 -
b100 *
b101 (
#370
b111 !
b111 #
b111 /
15
18
12
b101 0
b101 &
b101 -
b101 *
b110 (
#380
1M
1K
1D
0E
1G
1C
05
b1000 !
b1000 #
b1000 /
0=
b1100 .
1<
08
0@
1>
02
1:
b110 0
b110 &
b110 -
b110 *
b111 (
#390
b1001 !
b1001 #
b1001 /
15
18
12
b111 0
b111 &
b111 -
b111 *
b1000 (
#400
0K
0$
0C
0D
0L
05
1=
b0 .
0<
0E
0G
b1010 !
b1010 #
b1010 /
1M
0O
08
1@
0>
0H
1P
02
0:
0B
1J
b1000 0
b1000 &
b1000 -
b1000 *
b1001 (
#410
b1011 !
b1011 #
b1011 /
15
18
12
b1001 0
b1001 &
b1001 -
b1001 *
b1010 (
#420
1E
1C
05
b1100 !
b1100 #
b1100 /
0=
b100 .
1<
08
0@
1>
02
1:
b1010 0
b1010 &
b1010 -
b1010 *
b1011 (
#430
b1101 !
b1101 #
b1101 /
15
18
12
b1011 0
b1011 &
b1011 -
b1011 *
b1100 (
#440
0$
0L
1M
0O
0K
0C
0D
05
1=
b0 .
0<
b1110 !
b1110 #
b1110 /
1E
0G
08
1@
0>
1H
02
0:
1B
b1100 0
b1100 &
b1100 -
b1100 *
b1101 (
#450
b1111 !
b1111 #
b1111 /
15
18
12
b1101 0
b1101 &
b1101 -
b1101 *
b1110 (
#460
1$
1L
0M
1O
1K
1D
0E
1G
1C
05
b0 !
b0 #
b0 /
0=
b11100 .
1<
08
0@
1>
02
1:
b1110 0
b1110 &
b1110 -
b1110 *
b1111 (
#470
b1 !
b1 #
b1 /
15
18
12
b1111 0
b1111 &
b1111 -
b1111 *
b10000 (
#480
0C
0<
1=
0K
0$
0D
0L
0E
0G
0M
0O
0?
1@
0>
0H
0P
0;
02
0:
0B
0J
b11 !
b11 #
b11 /
15
b0 .
04
b0 0
18
06
11
b0 &
b0 -
b11 %
b11 ,
b11 )
b0 *
b10001 (
#490
1E
1C
1<
0=
1?
1;
b100 !
b100 #
b100 /
05
b110 .
14
08
16
12
b1 0
b1 &
b1 -
b1 *
b11 (
#500
0;
15
b100 .
04
b101 !
b101 #
b101 /
0=
0?
18
06
0@
1>
02
1:
b10 0
b10 &
b10 -
b10 *
b100 (
#510
1=
1;
b110 !
b110 #
b110 /
05
b110 .
14
08
16
12
b11 0
b11 &
b11 -
b11 *
b101 (
#520
0M
0K
0;
0C
0D
15
04
1=
0?
b0 .
0<
b111 !
b111 #
b111 /
1E
0G
18
06
1@
0>
1H
02
0:
1B
b100 0
b100 &
b100 -
b100 *
b110 (
#530
1M
1K
1D
0E
1G
1C
1<
0=
1?
1;
b1000 !
b1000 #
b1000 /
05
b1110 .
14
08
16
12
b101 0
b101 &
b101 -
b101 *
b111 (
#540
0;
15
b1100 .
04
b1001 !
b1001 #
b1001 /
0=
0?
18
06
0@
1>
02
1:
b110 0
b110 &
b110 -
b110 *
b1000 (
#550
1=
1;
b1010 !
b1010 #
b1010 /
05
b1110 .
14
08
16
12
b111 0
b111 &
b111 -
b111 *
b1001 (
#560
0K
0$
0;
0C
0D
0L
15
04
1=
0?
b0 .
0<
0E
0G
b1011 !
b1011 #
b1011 /
1M
0O
18
06
1@
0>
0H
1P
02
0:
0B
1J
b1000 0
b1000 &
b1000 -
b1000 *
b1010 (
#570
1E
1C
1<
0=
1?
1;
b1100 !
b1100 #
b1100 /
05
b110 .
14
08
16
12
b1001 0
b1001 &
b1001 -
b1001 *
b1011 (
#580
0;
15
b100 .
04
b1101 !
b1101 #
b1101 /
0=
0?
18
06
0@
1>
02
1:
b1010 0
b1010 &
b1010 -
b1010 *
b1100 (
#590
1=
1;
b1110 !
b1110 #
b1110 /
05
b110 .
14
08
16
12
b1011 0
b1011 &
b1011 -
b1011 *
b1101 (
#600
0$
0L
1M
0O
0K
0;
0C
0D
15
04
1=
0?
b0 .
0<
b1111 !
b1111 #
b1111 /
1E
0G
18
06
1@
0>
1H
02
0:
1B
b1100 0
b1100 &
b1100 -
b1100 *
b1110 (
#610
1$
1L
0M
1O
1K
1D
0E
1G
1C
1<
0=
1?
1;
b0 !
b0 #
b0 /
05
b11110 .
14
08
16
12
b1101 0
b1101 &
b1101 -
b1101 *
b1111 (
#620
0;
15
b11100 .
04
b1 !
b1 #
b1 /
0=
0?
18
06
0@
1>
02
1:
b1110 0
b1110 &
b1110 -
b1110 *
b10000 (
#630
1=
1;
b10 !
b10 #
b10 /
05
b11110 .
14
08
16
12
b1111 0
b1111 &
b1111 -
b1111 *
b10001 (
#640
0$
0K
0L
0D
0M
0O
0P
0;
0C
02
0:
0B
0J
05
04
0=
0?
b0 .
0<
b100 !
b100 #
b100 /
1E
0G
b0 0
08
06
0@
0>
1H
0F
01
09
1A
b0 &
b0 -
b100 %
b100 ,
b100 )
b0 *
b10010 (
#650
b101 !
b101 #
b101 /
15
18
12
b1 0
b1 &
b1 -
b1 *
b100 (
#660
05
b110 !
b110 #
b110 /
1=
08
1@
02
1:
b10 0
b10 &
b10 -
b10 *
b101 (
#670
b111 !
b111 #
b111 /
15
18
12
b11 0
b11 &
b11 -
b11 *
b110 (
#680
1M
1K
05
0=
b1000 !
b1000 #
b1000 /
0E
b1000 .
1D
08
0@
0H
1F
02
0:
1B
b100 0
b100 &
b100 -
b100 *
b111 (
#690
b1001 !
b1001 #
b1001 /
15
18
12
b101 0
b101 &
b101 -
b101 *
b1000 (
#700
05
b1010 !
b1010 #
b1010 /
1=
08
1@
02
1:
b110 0
b110 &
b110 -
b110 *
b1001 (
#710
b1011 !
b1011 #
b1011 /
15
18
12
b111 0
b111 &
b111 -
b111 *
b1010 (
#720
0$
0K
0L
05
0=
1E
b0 .
0D
b1100 !
b1100 #
b1100 /
1M
0O
08
0@
1H
0F
1P
02
0:
0B
1J
b1000 0
b1000 &
b1000 -
b1000 *
b1011 (
#730
b1101 !
b1101 #
b1101 /
15
18
12
b1001 0
b1001 &
b1001 -
b1001 *
b1100 (
#740
05
b1110 !
b1110 #
b1110 /
1=
08
1@
02
1:
b1010 0
b1010 &
b1010 -
b1010 *
b1101 (
#750
b1111 !
b1111 #
b1111 /
15
18
12
b1011 0
b1011 &
b1011 -
b1011 *
b1110 (
#760
1$
1L
0M
1O
1K
05
0=
b0 !
b0 #
b0 /
0E
b11000 .
1D
08
0@
0H
1F
02
0:
1B
b1100 0
b1100 &
b1100 -
b1100 *
b1111 (
#770
b1 !
b1 #
b1 /
15
18
12
b1101 0
b1101 &
b1101 -
b1101 *
b10000 (
#780
05
b10 !
b10 #
b10 /
1=
08
1@
02
1:
b1110 0
b1110 &
b1110 -
b1110 *
b10001 (
#790
b11 !
b11 #
b11 /
15
18
12
b1111 0
b1111 &
b1111 -
b1111 *
b10010 (
#800
0=
0$
0K
0L
1E
0D
0M
0O
0@
1H
0F
0P
0;
02
0:
0B
0J
b101 !
b101 #
b101 /
15
b0 .
04
b0 0
18
06
11
b0 &
b0 -
b101 %
b101 ,
b101 )
b0 *
b10011 (
#810
1=
1;
b110 !
b110 #
b110 /
05
b10 .
14
08
16
12
b1 0
b1 &
b1 -
b1 *
b101 (
#820
0M
0K
0D
1E
0G
0C
0;
0<
15
b0 .
04
b111 !
b111 #
b111 /
1=
0?
18
06
1@
02
1:
b10 0
b10 &
b10 -
b10 *
b110 (
#830
1M
1K
1D
0E
1G
1C
1<
0=
1?
1;
b1000 !
b1000 #
b1000 /
05
b1110 .
14
08
16
12
b11 0
b11 &
b11 -
b11 *
b111 (
#840
0C
0;
0<
15
b1000 .
04
0=
0?
b1001 !
b1001 #
b1001 /
0E
0G
18
06
0@
0H
1F
02
0:
1B
b100 0
b100 &
b100 -
b100 *
b1000 (
#850
1=
1;
b1010 !
b1010 #
b1010 /
05
b1010 .
14
08
16
12
b101 0
b101 &
b101 -
b101 *
b1001 (
#860
0E
0C
0;
0<
15
b1000 .
04
b1011 !
b1011 #
b1011 /
1=
0?
18
06
1@
02
1:
b110 0
b110 &
b110 -
b110 *
b1010 (
#870
1E
1C
1<
0=
1?
1;
b1100 !
b1100 #
b1100 /
05
b1110 .
14
08
16
12
b111 0
b111 &
b111 -
b111 *
b1011 (
#880
0C
0$
0;
0<
0K
0L
15
04
0=
0?
1E
0G
b0 .
0D
b1101 !
b1101 #
b1101 /
1M
0O
18
06
0@
1H
0F
1P
02
0:
0B
1J
b1000 0
b1000 &
b1000 -
b1000 *
b1100 (
#890
1=
1;
b1110 !
b1110 #
b1110 /
05
b10 .
14
08
16
12
b1001 0
b1001 &
b1001 -
b1001 *
b1101 (
#900
0$
0L
1M
0O
0K
0D
1E
0G
0C
0;
0<
15
b0 .
04
b1111 !
b1111 #
b1111 /
1=
0?
18
06
1@
02
1:
b1010 0
b1010 &
b1010 -
b1010 *
b1110 (
#910
1$
1L
0M
1O
1K
1D
0E
1G
1C
1<
0=
1?
1;
b0 !
b0 #
b0 /
05
b11110 .
14
08
16
12
b1011 0
b1011 &
b1011 -
b1011 *
b1111 (
#920
0C
0;
0<
15
b11000 .
04
0=
0?
b1 !
b1 #
b1 /
0E
0G
18
06
0@
0H
1F
02
0:
1B
b1100 0
b1100 &
b1100 -
b1100 *
b10000 (
#930
1=
1;
b10 !
b10 #
b10 /
05
b11010 .
14
08
16
12
b1101 0
b1101 &
b1101 -
b1101 *
b10001 (
#940
0E
0C
0;
0<
15
b11000 .
04
b11 !
b11 #
b11 /
1=
0?
18
06
1@
02
1:
b1110 0
b1110 &
b1110 -
b1110 *
b10010 (
#950
1E
1C
1<
0=
1?
1;
b100 !
b100 #
b100 /
05
b11110 .
14
08
16
12
b1111 0
b1111 &
b1111 -
b1111 *
b10011 (
#960
0$
0C
0K
0L
0<
1E
0G
0D
0M
0O
1H
0F
0P
0;
02
0:
0B
0J
05
b0 .
04
b110 !
b110 #
b110 /
1=
0?
b0 0
08
06
1@
0>
01
19
b0 &
b0 -
b110 %
b110 ,
b110 )
b0 *
b10100 (
#970
b111 !
b111 #
b111 /
15
18
12
b1 0
b1 &
b1 -
b1 *
b110 (
#980
1M
1K
1D
0E
1G
1C
05
b1000 !
b1000 #
b1000 /
0=
b1100 .
1<
08
0@
1>
02
1:
b10 0
b10 &
b10 -
b10 *
b111 (
#990
b1001 !
b1001 #
b1001 /
15
18
12
b11 0
b11 &
b11 -
b11 *
b1000 (
#1000
0C
05
1=
b1000 .
0<
b1010 !
b1010 #
b1010 /
0E
0G
08
1@
0>
0H
1F
02
0:
1B
b100 0
b100 &
b100 -
b100 *
b1001 (
#1010
b1011 !
b1011 #
b1011 /
15
18
12
b101 0
b101 &
b101 -
b101 *
b1010 (
#1020
1E
1C
05
b1100 !
b1100 #
b1100 /
0=
b1100 .
1<
08
0@
1>
02
1:
b110 0
b110 &
b110 -
b110 *
b1011 (
#1030
b1101 !
b1101 #
b1101 /
15
18
12
b111 0
b111 &
b111 -
b111 *
b1100 (
#1040
0$
0C
0K
0L
05
1=
0<
1E
0G
b0 .
0D
b1110 !
b1110 #
b1110 /
1M
0O
08
1@
0>
1H
0F
1P
02
0:
0B
1J
b1000 0
b1000 &
b1000 -
b1000 *
b1101 (
#1050
b1111 !
b1111 #
b1111 /
15
18
12
b1001 0
b1001 &
b1001 -
b1001 *
b1110 (
#1060
1$
1L
0M
1O
1K
1D
0E
1G
1C
05
b0 !
b0 #
b0 /
0=
b11100 .
1<
08
0@
1>
02
1:
b1010 0
b1010 &
b1010 -
b1010 *
b1111 (
#1070
b1 !
b1 #
b1 /
15
18
12
b1011 0
b1011 &
b1011 -
b1011 *
b10000 (
#1080
0C
05
1=
b11000 .
0<
b10 !
b10 #
b10 /
0E
0G
08
1@
0>
0H
1F
02
0:
1B
b1100 0
b1100 &
b1100 -
b1100 *
b10001 (
#1090
b11 !
b11 #
b11 /
15
18
12
b1101 0
b1101 &
b1101 -
b1101 *
b10010 (
#1100
1E
1C
05
b100 !
b100 #
b100 /
0=
b11100 .
1<
08
0@
1>
02
1:
b1110 0
b1110 &
b1110 -
b1110 *
b10011 (
#1110
b101 !
b101 #
b101 /
15
18
12
b1111 0
b1111 &
b1111 -
b1111 *
b10100 (
#1120
0C
0<
1=
0$
0K
0L
1E
0G
0D
0M
0O
0?
1@
0>
1H
0F
0P
0;
02
0:
0B
0J
b111 !
b111 #
b111 /
15
b0 .
04
b0 0
18
06
11
b0 &
b0 -
b111 %
b111 ,
b111 )
b0 *
b10101 (
#1130
1M
1K
1D
0E
1G
1C
1<
0=
1?
1;
b1000 !
b1000 #
b1000 /
05
b1110 .
14
08
16
12
b1 0
b1 &
b1 -
b1 *
b111 (
#1140
0;
15
b1100 .
04
b1001 !
b1001 #
b1001 /
0=
0?
18
06
0@
1>
02
1:
b10 0
b10 &
b10 -
b10 *
b1000 (
#1150
1=
1;
b1010 !
b1010 #
b1010 /
05
b1110 .
14
08
16
12
b11 0
b11 &
b11 -
b11 *
b1001 (
#1160
0;
0C
15
04
1=
0?
b1000 .
0<
b1011 !
b1011 #
b1011 /
0E
0G
18
06
1@
0>
0H
1F
02
0:
1B
b100 0
b100 &
b100 -
b100 *
b1010 (
#1170
1E
1C
1<
0=
1?
1;
b1100 !
b1100 #
b1100 /
05
b1110 .
14
08
16
12
b101 0
b101 &
b101 -
b101 *
b1011 (
#1180
0;
15
b1100 .
04
b1101 !
b1101 #
b1101 /
0=
0?
18
06
0@
1>
02
1:
b110 0
b110 &
b110 -
b110 *
b1100 (
#1190
1=
1;
b1110 !
b1110 #
b1110 /
05
b1110 .
14
08
16
12
b111 0
b111 &
b111 -
b111 *
b1101 (
#1200
0$
0;
0C
0K
0L
15
04
1=
0?
0<
1E
0G
b0 .
0D
b1111 !
b1111 #
b1111 /
1M
0O
18
06
1@
0>
1H
0F
1P
02
0:
0B
1J
b1000 0
b1000 &
b1000 -
b1000 *
b1110 (
#1210
1$
1L
0M
1O
1K
1D
0E
1G
1C
1<
0=
1?
1;
b0 !
b0 #
b0 /
05
b11110 .
14
08
16
12
b1001 0
b1001 &
b1001 -
b1001 *
b1111 (
#1220
0;
15
b11100 .
04
b1 !
b1 #
b1 /
0=
0?
18
06
0@
1>
02
1:
b1010 0
b1010 &
b1010 -
b1010 *
b10000 (
#1230
1=
1;
b10 !
b10 #
b10 /
05
b11110 .
14
08
16
12
b1011 0
b1011 &
b1011 -
b1011 *
b10001 (
#1240
0;
0C
15
04
1=
0?
b11000 .
0<
b11 !
b11 #
b11 /
0E
0G
18
06
1@
0>
0H
1F
02
0:
1B
b1100 0
b1100 &
b1100 -
b1100 *
b10010 (
#1250
1E
1C
1<
0=
1?
1;
b100 !
b100 #
b100 /
05
b11110 .
14
08
16
12
b1101 0
b1101 &
b1101 -
b1101 *
b10011 (
#1260
0;
15
b11100 .
04
b101 !
b101 #
b101 /
0=
0?
18
06
0@
1>
02
1:
b1110 0
b1110 &
b1110 -
b1110 *
b10100 (
#1270
1=
1;
b110 !
b110 #
b110 /
05
b11110 .
14
08
16
12
b1111 0
b1111 &
b1111 -
b1111 *
b10101 (
#1280
0$
0L
0;
0C
0K
02
0:
0B
0J
05
04
0=
0?
0<
0E
0G
b0 .
0D
b1000 !
b1000 #
b1000 /
1M
0O
b0 0
08
06
0@
0>
0H
0F
1P
0N
01
09
0A
1I
b0 &
b0 -
b1000 %
b1000 ,
b1000 )
b0 *
b10110 (
#1290
b1001 !
b1001 #
b1001 /
15
18
12
b1 0
b1 &
b1 -
b1 *
b1000 (
#1300
05
b1010 !
b1010 #
b1010 /
1=
08
1@
02
1:
b10 0
b10 &
b10 -
b10 *
b1001 (
#1310
b1011 !
b1011 #
b1011 /
15
18
12
b11 0
b11 &
b11 -
b11 *
b1010 (
#1320
05
0=
b1100 !
b1100 #
b1100 /
1E
08
0@
1H
02
0:
1B
b100 0
b100 &
b100 -
b100 *
b1011 (
#1330
b1101 !
b1101 #
b1101 /
15
18
12
b101 0
b101 &
b101 -
b101 *
b1100 (
#1340
05
b1110 !
b1110 #
b1110 /
1=
08
1@
02
1:
b110 0
b110 &
b110 -
b110 *
b1101 (
#1350
b1111 !
b1111 #
b1111 /
15
18
12
b111 0
b111 &
b111 -
b111 *
b1110 (
#1360
1$
05
0=
0E
b0 !
b0 #
b0 /
0M
b10000 .
1L
08
0@
0H
0P
1N
02
0:
0B
1J
b1000 0
b1000 &
b1000 -
b1000 *
b1111 (
#1370
b1 !
b1 #
b1 /
15
18
12
b1001 0
b1001 &
b1001 -
b1001 *
b10000 (
#1380
05
b10 !
b10 #
b10 /
1=
08
1@
02
1:
b1010 0
b1010 &
b1010 -
b1010 *
b10001 (
#1390
b11 !
b11 #
b11 /
15
18
12
b1011 0
b1011 &
b1011 -
b1011 *
b10010 (
#1400
05
0=
b100 !
b100 #
b100 /
1E
08
0@
1H
02
0:
1B
b1100 0
b1100 &
b1100 -
b1100 *
b10011 (
#1410
b101 !
b101 #
b101 /
15
18
12
b1101 0
b1101 &
b1101 -
b1101 *
b10100 (
#1420
05
b110 !
b110 #
b110 /
1=
08
1@
02
1:
b1110 0
b1110 &
b1110 -
b1110 *
b10101 (
#1430
b111 !
b111 #
b111 /
15
18
12
b1111 0
b1111 &
b1111 -
b1111 *
b10110 (
#1440
0=
0$
0E
1M
0L
0@
0H
1P
0N
0;
02
0:
0B
0J
b1001 !
b1001 #
b1001 /
15
b0 .
04
b0 0
18
06
11
b0 &
b0 -
b1001 %
b1001 ,
b1001 )
b0 *
b10111 (
#1450
1=
1;
b1010 !
b1010 #
b1010 /
05
b10 .
14
08
16
12
b1 0
b1 &
b1 -
b1 *
b1001 (
#1460
0E
0C
0;
0<
15
b0 .
04
b1011 !
b1011 #
b1011 /
1=
0?
18
06
1@
02
1:
b10 0
b10 &
b10 -
b10 *
b1010 (
#1470
1E
1C
1<
0=
1?
1;
b1100 !
b1100 #
b1100 /
05
b110 .
14
08
16
12
b11 0
b11 &
b11 -
b11 *
b1011 (
#1480
0$
0L
1M
0O
0C
0K
0;
0<
0D
15
b0 .
04
0=
0?
b1101 !
b1101 #
b1101 /
1E
0G
18
06
0@
1H
02
0:
1B
b100 0
b100 &
b100 -
b100 *
b1100 (
#1490
1=
1;
b1110 !
b1110 #
b1110 /
05
b10 .
14
08
16
12
b101 0
b101 &
b101 -
b101 *
b1101 (
